odoo10_addon_l10n_us_account_profile-10.0.0.0.2-py2.7-nspkg.pth
odoo/addons/l10n_us_account_profile/README.rst
odoo/addons/l10n_us_account_profile/__init__.py
odoo/addons/l10n_us_account_profile/__manifest__.py
odoo/addons/l10n_us_account_profile/i18n/l10n_us_account_profile.pot
odoo/addons/l10n_us_account_profile/static/description/icon.png
odoo10_addon_l10n_us_account_profile-10.0.0.0.2.dist-info/METADATA
odoo10_addon_l10n_us_account_profile-10.0.0.0.2.dist-info/RECORD
odoo10_addon_l10n_us_account_profile-10.0.0.0.2.dist-info/WHEEL
odoo10_addon_l10n_us_account_profile-10.0.0.0.2.dist-info/namespace_packages.txt
odoo10_addon_l10n_us_account_profile-10.0.0.0.2.dist-info/top_level.txt
