Metadata-Version: 2.1
Name: odoo10-addon-l10n-us-account-profile
Version: 10.0.0.0.2
Summary: Additional features to manage US accounting in Odoo
Home-page: http://www.ursainfosystems.com
Author: Ursa Information Systems, Odoo Community Association (OCA)
Author-email: support@odoo-community.org
License: AGPL-3
Platform: UNKNOWN
Classifier: Programming Language :: Python
Classifier: Framework :: Odoo
Classifier: License :: OSI Approved :: GNU Affero General Public License v3
Requires-Python: ~=2.7
Requires-Dist: odoo10-addon-account-due-list
Requires-Dist: odoo10-addon-account-payment-batch-process
Requires-Dist: odoo10-addon-account-payment-credit-card
Requires-Dist: odoo10-addon-account-reversal
Requires-Dist: odoo10-addon-l10n-us-check-writing-address
Requires-Dist: odoo10-addon-l10n-us-form-1099
Requires-Dist: odoo10-addon-partner-aging
Requires-Dist: odoo10-addon-partner-daytopay
Requires-Dist: odoo (<10.1dev,>=10.0)
